luapatt.py
luapatt-0.9.0b5.dist-info/DESCRIPTION.rst
luapatt-0.9.0b5.dist-info/METADATA
luapatt-0.9.0b5.dist-info/RECORD
luapatt-0.9.0b5.dist-info/WHEEL
luapatt-0.9.0b5.dist-info/metadata.json
luapatt-0.9.0b5.dist-info/top_level.txt
