Metadata-Version: 2.0
Name: luapatt
Version: 0.9.0b5
Summary: Python implementation of Lua-style pattern matching
Home-page: https://github.com/jcgoble3/luapatt
Author: Jonathan Goble
Author-email: jcgoble3@gmail.com
License: MIT
Keywords: Lua pattern matching regex regular expressions
Platform: UNKNOWN
Classifier: Development Status :: 4 - Beta
Classifier: Intended Audience :: Developers
Classifier: License :: OSI Approved :: MIT License
Classifier: Operating System :: OS Independent
Classifier: Programming Language :: Python :: 3
Classifier: Programming Language :: Python :: 3 :: Only
Classifier: Programming Language :: Python :: 3.3
Classifier: Programming Language :: Python :: 3.4
Classifier: Programming Language :: Python :: 3.5
Classifier: Topic :: Software Development :: Libraries :: Python Modules
Classifier: Topic :: Text Processing :: General
Provides-Extra: test
Requires-Dist: pytest; extra == 'test'
